bastionlab_server/__init__.py
bastionlab_server/server.py
bastionlab_server/version.py
bastionlab_server-0.3.7.dist-info/METADATA
bastionlab_server-0.3.7.dist-info/WHEEL
bastionlab_server-0.3.7.dist-info/top_level.txt
bastionlab_server-0.3.7.dist-info/RECORD
