Metadata-Version: 2.1
Name: bastionlab_server
Version: 0.3.7
Summary: Server for BastionLab Confidential Analytics.
Author: Mithril Security
Author-email: contact@mithrilsecurity.io
Keywords: confidential computing training client enclave amd-sev machine learning
Classifier: Programming Language :: Python :: 3
